leetbuddy.py
leetbuddy-0.1.1.dist-info/METADATA
leetbuddy-0.1.1.dist-info/WHEEL
leetbuddy-0.1.1.dist-info/entry_points.txt
leetbuddy-0.1.1.dist-info/top_level.txt
leetbuddy-0.1.1.dist-info/RECORD
