Metadata-Version: 2.4
Name: leetbuddy
Version: 0.1.1
Summary: A CLI tool for LeetCode daily problems and submissions
Home-page: https://github.com/yourusername/leetbuddy
Author: Pradeep Elamurugu
Author-email: your.email@example.com
Classifier: Programming Language :: Python :: 3
Classifier: License :: OSI Approved :: MIT License
Classifier: Operating System :: OS Independent
Requires-Python: >=3.7
Requires-Dist: click
Requires-Dist: requests
Requires-Dist: urllib3
Dynamic: author
Dynamic: author-email
Dynamic: classifier
Dynamic: description
Dynamic: description-content-type
Dynamic: home-page
Dynamic: requires-dist
Dynamic: requires-python
Dynamic: summary
